Metadata-Version: 2.1
Name: odoo12-addon-maintenance-equipment-custom-info
Version: 12.0.2.0.0
Summary: Add custom info in equipments
Home-page: https://github.com/OCA/maintenance
Author: Odoo Community Association (OCA), Solvos
Author-email: support@odoo-community.org
License: AGPL-3
Platform: UNKNOWN
Classifier: Programming Language :: Python
Classifier: Framework :: Odoo
Classifier: License :: OSI Approved :: GNU Affero General Public License v3
Requires-Python: >=3.5
Requires-Dist: odoo12-addon-base-custom-info
Requires-Dist: odoo (<12.1dev,>=12.0a)
